ontu_parser/__init__.py
ontu_parser/classes/__init__.py
ontu_parser/classes/base.py
ontu_parser/classes/dataclasses.py
ontu_parser/classes/enums.py
ontu_parser/classes/js_parser.py
ontu_parser/classes/parser.py
ontu_parser/classes/sender.py
ontu_parser/example.py
rozklad_ontu_parser_makisukurisu-0.1.3.0.dist-info/METADATA
rozklad_ontu_parser_makisukurisu-0.1.3.0.dist-info/WHEEL
rozklad_ontu_parser_makisukurisu-0.1.3.0.dist-info/entry_points.txt
rozklad_ontu_parser_makisukurisu-0.1.3.0.dist-info/licenses/LICENSE
rozklad_ontu_parser_makisukurisu-0.1.3.0.dist-info/RECORD
