Metadata-Version: 2.1
Name: rozklad-ontu-parser-makisukurisu
Version: 0.1.3.0
Summary: Package for parsing data from rozklad.ontu.edu.ua
Author-Email: Pavlo Pohorieltsev <49622129+makisukurisu@users.noreply.github.com>
Classifier: Programming Language :: Python :: 3
Classifier: License :: OSI Approved :: BSD License
Classifier: Operating System :: OS Independent
Classifier: Natural Language :: English
Project-URL: Homepage, https://github.com/Wandering-Cursor/rozklad-ontu-parser
Project-URL: Bug Tracker, https://github.com/Wandering-Cursor/rozklad-ontu-parser/issues
Requires-Python: >=3.11
Requires-Dist: attrs<25.0.0,>=23.2.0
Requires-Dist: beautifulsoup4<5.0.0,>=4.12.3
Requires-Dist: requests<3.0.0,>=2.31.0
